{
  "generic": {
    "type": "generic_crafting_vehicle",
    "forwardsDamageMultiplier": 0.0,
    "canBePlacedOnGround": true,
    "width": 2.0,
    "height": 1.0,
    "mass": 300
  },
  "definitions": [
    {
      "subName": "",
      "name": "Frame",
      "extraMaterialLists": [
        []
      ]
    }
  ],
  "rendering": {
    "animatedObjects": [
      {
        "objectName": "frame_m",
        "animations": [
          {
            "animationType": "visibility",
            "variable": "part_onvehicle"
          },
          {
            "animationType": "translation",
            "variable": "!part_onvehicle",
            "centerPoint": [0.0,0.0,0.0],
            "axis": [0.0,0.0,-1.75]
          }
        ]
      },
      {
        "objectName": "frame_f",
        "animations": [
          {
            "animationType": "visibility",
            "variable": "!part_onvehicle"
          },
          {
            "animationType": "translation",
            "variable": "!part_onvehicle",
            "centerPoint": [0.0,0.0,0.0],
            "axis": [0.0,0.0,-1.75]
          }
        ]
      }
    ],
    "lightObjects": [],
    "particles": [],
    "modelType": "obj"
  },
  "general": {
    "name": "Crafting Item",
    "description": "Used for assembling vehicles\n§5§oCrafted in the Vehicle Parts Assembly bench",
    "health": 30,
    "materialLists": [
      [
        "oredict:ingotIron:7"
      ]
    ],
    "radarWidth": 0.0,
    "radarRange": 0.0
  }
}
