{
  "interactable": {
    "interactionType": "crate",
    "feedsVehicles": false,
    "inventoryUnits": 6
  },
  "definitions": [
    {
      "subName": "",
      "name": "Shipping Container [Coca Cola]",
      "extraMaterials": []
    }
  ],
  "prefixFolders": "",
  "packID": "ivv",
  "systemName": "container_pootis",
  "classification": "PART",
  "general": {
    "type": "interactable_container_single",
    "modelName": "containerflat",
    "name": "Shipping Container [Coca Cola]",
    "description" : "With 30% more christmas spirit, and 15% more secret ingredients!",
    "materials": ["minecraft:iron_block:-1:8"]
  }
}
