{
  "generic": {
    "type": "generic_lightbar",
    "width": 0.5,
    "height": 0.25
  },
  "parts": [
    {
      "pos": [0.0,0.5,0.0],
      "isController": true,
      "types": ["seat_furniture"]
    }
  ],
  "definitions": [
    {
      "subName": "",
      "name": "Pure Concept of Mr Bean's Wild Ride",
      "extraMaterials": []
    }
  ],
  "rendering": {
    "lightObjects": [],
    "modelType": "obj"
  },
  "general": {
    "name": "Pure Concept of Mr Bean's Wild Ride",
    "description": "magic. *snort snort*",
    "health": 100,
    "materials": ["minecraft:air:0:1"]
  }
}