{
  "generic": {
    "type": "seat",
    "width": 1.0,
    "height": 0.875,
    "mass": 40,
        "activeAnimations": [
          {
            "animationType": "visibility",
            "variable": "part_present_2"
          }
        ]
  },
  "seat": {},
  "parts": [
    {
      "pos": [0.0,-0.0025,0.0],
      "maxValue": 1.0,
      "types": ["generic_npc"]
    },
    {
      "pos": [0.0,-0.1,0.15],
      "rot": [0.0,90.0,0.0],
      "maxValue": 3.0,
      "types": [
        "interactable_luggage"
      ],
      "interactableVariables": [
        [
          "!seat_occupied"
        ]
      ],
      "animations": [
        {
          "animationType": "translation",
          "variable": "!part_present_2",
          "axis": [0.0,0.375,0.0]
        }
      ]
    }
  ],
  "definitions": [
    {
      "subName": "",
      "name": "Truck Seat",
      "extraMaterialLists": [
        []
      ]
    }
  ],
  "rendering": {
    "lightObjects": [],
    "particles": [],
    "modelType": "obj"
  },
  "general": {
    "name": "Truck Seat",
    "stackSize": 64,
    "radarWidth": 0.0,
    "radarRange": 0.0,
    "health": 100,
    "materialLists": [
      ["oredict:ingotIron:2","oredict:leather:3"]
    ]
  }
}
