{
  "generic": {
    "type": "generic_licenseplate_us",
    "width": 0.25,
    "height": 0.25,
    "mustBeRemovedByScrewdriver": true
  },
  "definitions": [
    {
      "subName": "",
      "modelName": "licenseplate",
      "name": "License Plate [State]",
      "extraMaterials": []
    }
  ],
  "rendering": {
    "textObjects": [
      {
        "pos": [0.0,0.05,0.00025],
        "rot": [0.0,0.0,0.0],
        "scale": 0.175,
        "fieldName": "License Plate",
        "defaultText": "STATE123",
        "maxLength": 8,
        "color": "3C260D"
      }
    ],
    "lightObjects": [],
    "particles": [],
    "modelType": "obj"
  },
  "general": {
    "name": "License Plate [State]",
    "description": "Good for tow trucks, police cruisers or ambulances!",
    "stackSize": 64,
    "health": 100,
    "materials": ["minecraft:iron_ingot:0:1"]
  }
}
